passcat/__init__.py
passcat/passcat.py
passcat/wordlists/eff.txt
passcat/wordlists/english.txt
passcat/wordlists/french.txt
passcat/wordlists/german.txt
passcat/wordlists/indonesian.txt
passcat/wordlists/italian.txt
passcat/wordlists/spanish.txt
passcat-0.1.2.dist-info/LICENSE.txt
passcat-0.1.2.dist-info/METADATA
passcat-0.1.2.dist-info/WHEEL
passcat-0.1.2.dist-info/entry_points.txt
passcat-0.1.2.dist-info/top_level.txt
passcat-0.1.2.dist-info/RECORD
