Metadata-Version: 2.1
Name: passcat
Version: 0.1.2
Summary: Passcat lets you generate cryptographically secure, memorable passphrases.
Home-page: https://github.com/iamcryptoki/passcat
Author: Gael Gentil
Author-email: iamcryptoki@gmail.com
License: MIT
Keywords: passphrase,password,secret,security,words
Platform: UNKNOWN
Requires-Dist: docopt
